django_pass_gen_safe-0.1.1.dist-info/licenses/LICENSE
management/__init__.py
management/add_to_safe.py
management/generate_password.py
management/list_safe.py
management/commands/__init__.py
management/commands/generate_password.py
django_pass_gen_safe-0.1.1.dist-info/METADATA
django_pass_gen_safe-0.1.1.dist-info/WHEEL
django_pass_gen_safe-0.1.1.dist-info/top_level.txt
django_pass_gen_safe-0.1.1.dist-info/RECORD
